Endeless/Songs-dataset.csv
Endeless/__init__.py
Endeless/__main__.py
Endeless/chord_recognition.py
Endeless/dataset_path.txt
Endeless/dataset_update.py
Endeless/endeless.py
Endeless/endeless_worker.py
Endeless/dataset/Songs-dataset.csv
Endeless/dataset/__init__.py
Endeless/dataset/dataset_path.txt
Endeless/dataset/dataset_update.py
Endeless/songs/PLACE SONGS HERE.txt
Endeless/workers/__init__.py
Endeless/workers/chord_recognition.py
Endeless/workers/endeless_worker.py
Endeless-0.1.dist-info/LICENSE
Endeless-0.1.dist-info/METADATA
Endeless-0.1.dist-info/WHEEL
Endeless-0.1.dist-info/entry_points.txt
Endeless-0.1.dist-info/top_level.txt
Endeless-0.1.dist-info/RECORD
