Metadata-Version: 2.1
Name: Endeless
Version: 0.1
Summary: Create playlists with seamless music transitions.
Home-page: https://github.com/Aurbcd/Endeless
Author: Aurbcd
Author-email: contact.keyofmagic@gmail.com
License: UNKNOWN
Keywords: music,youtube,mp3,playlist,seamless
Platform: UNKNOWN
Classifier: Programming Language :: Python :: 3.8
Classifier: License :: OSI Approved :: MIT License
Classifier: Topic :: Multimedia
Classifier: Topic :: Multimedia :: Sound/Audio
Classifier: Topic :: Utilities
Requires-Python: >=3.8
Requires-Dist: pydub
Requires-Dist: librosa
Requires-Dist: numpy (>=1.17.*)
Requires-Dist: pandas
Requires-Dist: libfmp
Requires-Dist: requests
Requires-Dist: beautifulsoup4
Requires-Dist: mutagen
